make_psc/instruction_memory.sv


module instruction_memory (
    input logic [31:0] im_a,
    output logic [31:0] im_rd 
);

logic [31:0] inst [0:7];                  //fake sonra 128
//fake ayrıca komut yükleme sistemi olcak

//assign im_rd = inst[im_a]; normali bu düzelticem
assign im_rd = im_a;


endmodule

make_psc/control.sv


module control (
    input logic clk,                            //fake
    input  logic [6:0] op,
    input  logic [2:0] funct3, 
    input logic [6:0] funct7,
    output logic r_cd, dm_cd, m_cd1, m_cd2, d_cd1, d_cd2,
    output  logic [1:0] e_cd,
    output  logic [2:0] alu_cd 
);

assign e_cd = 2'b01;
assign alu_cd = 3'b001;
assign m_cd1 = 1;
assign d_cd2 = 1;


  always_ff @(posedge clk) begin 
    r_cd = ~r_cd;                       //fake
  end

  always_ff @(negedge clk) begin
    dm_cd = ~dm_cd;                       //fake
  end


endmodule

make_psc/data_memory.sv


module data_memory (
    input logic clk, dm_cd,
    input logic [31:0] dm_a,
    input logic [31:0] dm_wd,
    output logic [31:0] dm_rd 
);

logic [31:0] data [0:31];                 

assign dm_rd = data[dm_a];

  always @(negedge clk) begin
  
    if(dm_cd==1) begin
      data[dm_a] = dm_wd;
    end
    
  end

endmodule

make_psc/ALU.sv


module ALU (
    input  logic [31:0] alu_a, alu_b,
    input  logic [2:0] alu_cd, 
    output logic [31:0] alu_rd
);

  always_comb begin
    if(alu_cd==3'b001)
      alu_rd = alu_a | alu_b;
    else
      alu_rd = 0;

  end
endmodule

make_psc/extender.sv
import riscv_pkg::*;

module extender (
    input  logic [24:0] e_a,
    input  logic [1:0] e_cd, 
    output logic [31:0] e_rd
);

  always_comb begin
      case (e_cd)
          IMM_I:   e_rd = {{20{e_a[24]}}, e_a[24:13]};
          IMM_S:   e_rd = {{20{e_a[24]}}, e_a[24:18], e_a[4:0]};
          IMM_U:   e_rd = {e_a[24:5], 12'b0};
          default: e_rd = '0;
      endcase
  end

endmodule

make_psc/register.sv


module register (
    input  logic clk, r_cd,
    input  logic [4:0]  r_a1,
    input  logic [4:0]  r_a2,
    input  logic [4:0]  r_a3,
    input  logic [31:0] r_wd3,
    output logic [31:0] r_rd1,
    output logic [31:0] r_rd2
);

logic [31:0] register [0:31];

assign r_rd1 = register[r_a1];
assign r_rd2 = register[r_a2];

  always @(posedge clk) begin
  
    if(r_cd==1) begin
      register[r_a3] = r_wd3;
      //register[r_a1] = register[r_a1]+1; //fake
    end

  end
endmodule

make_psc/top.sv
module mux (
  input logic [31:0] a1, a2,
  input logic m_cd,  
  output logic [31:0] m_rd
);
  always_comb begin
    if(m_cd==0)
      m_rd = a1;
    else
      m_rd = a2;
  end
endmodule

module demux (
  input logic [31:0] a1,
  input logic d_cd,  
  output logic [31:0] rd1, rd2
);
  always_comb begin
    if(d_cd==0) begin
      rd1 = a1;
      rd2 = 0;
    end
    else begin
      rd1 = 0;
      rd2 = a1;
    end
  end
endmodule

module top (input logic clk);
logic [4:0] r_a1, r_a2, r_a3;
logic [31:0] r_rd1, r_rd2, r_wd3;

logic [24:0] e_a;
logic [31:0] e_rd;
logic [31:0] alu_a, alu_b, alu_rd;

logic r_cd, dm_cd, m_cd1, m_cd2, d_cd1, d_cd2;
logic [1:0] e_cd;
logic [2:0] alu_cd;


logic [31:0] dm_a, dm_rd, dm_wd;
logic [31:0] im_rd;
logic [31:0] im_a= 32'b0000000_01001_00011_000_00101_0000000;   //fake


register r_0(.clk(clk), .r_cd(r_cd), .r_a1(r_a1), .r_a2(r_a2), .r_a3(r_a3),
 .r_wd3(r_wd3), .r_rd1(r_rd1), .r_rd2(r_rd2));

extender e_0(.e_a(e_a), .e_cd(e_cd), .e_rd(e_rd));

ALU alu_0(.alu_a(alu_a), .alu_b(alu_b), .alu_cd(alu_cd), .alu_rd(alu_rd));

data_memory m_data(.clk(clk), .dm_cd(dm_cd), .dm_a(dm_a), .dm_wd (dm_wd),
  .dm_rd(dm_rd));

control c_0(.op(im_rd[6:0]), .funct3(im_rd[14:12]), .funct7(im_rd[31:25]),
.r_cd(r_cd), .dm_cd(dm_cd), .m_cd1(m_cd1), .m_cd2(m_cd2), .d_cd1(d_cd1),
.d_cd2(d_cd2), .e_cd(e_cd), .alu_cd(alu_cd)
, .clk(clk)                                             //fake
);

instruction_memory m_inst(.im_a(im_a), .im_rd(im_rd));   //fake


assign e_a = im_rd[31:7];
assign r_a1 = im_rd[19:15];
assign r_a2 = im_rd[24:20];
assign r_a3 = im_rd[11:7];
assign alu_a = r_rd1;

mux mux_1 (.a1(demux1_out1), .a2(e_rd), .m_cd(m_cd1), .m_rd(alu_b));
mux mux_2 (.a1(demux2_out2), .a2(dm_rd), .m_cd(m_cd2), .m_rd(r_wd3));

logic [31:0] demux1_out1, demux2_out2;
demux demux_1 (.a1(r_rd2), .d_cd(d_cd1), .rd1(demux1_out1), .rd2(dm_wd));
demux demux_2 (.a1(alu_rd), .d_cd(d_cd2), .rd1(dm_a), .rd2(demux2_out2));

  final begin
    $display("Simulasyon bitti. Toplam çalışma süresi : %0t", $time);
    $display("Register 1 output : %0h", r_rd1);
    $display("Register 2 output : %0h", r_rd2);
  end

endmodule

dump.vcd
$version Generated by VerilatedVcd $end
$timescale 1ps $end
 $scope module TOP $end
  $var wire 1 R clk $end
  $scope module top $end
   $var wire 1 R clk $end
   $var wire 5 T r_a1 [4:0] $end
   $var wire 5 U r_a2 [4:0] $end
   $var wire 5 V r_a3 [4:0] $end
   $var wire 32 " r_rd1 [31:0] $end
   $var wire 32 # r_rd2 [31:0] $end
   $var wire 32 $ r_wd3 [31:0] $end
   $var wire 25 W e_a [24:0] $end
   $var wire 32 X e_rd [31:0] $end
   $var wire 32 " alu_a [31:0] $end
   $var wire 32 X alu_b [31:0] $end
   $var wire 32 % alu_rd [31:0] $end
   $var wire 1 & r_cd $end
   $var wire 1 S dm_cd $end
   $var wire 1 Y m_cd1 $end
   $var wire 1 Z m_cd2 $end
   $var wire 1 [ d_cd1 $end
   $var wire 1 Y d_cd2 $end
   $var wire 2 \ e_cd [1:0] $end
   $var wire 3 ] alu_cd [2:0] $end
   $var wire 32 ^ dm_a [31:0] $end
   $var wire 32 ' dm_rd [31:0] $end
   $var wire 32 ( dm_wd [31:0] $end
   $var wire 32 _ im_rd [31:0] $end
   $var wire 32 _ im_a [31:0] $end
   $var wire 32 ) demux1_out1 [31:0] $end
   $var wire 32 % demux2_out2 [31:0] $end
   $scope module alu_0 $end
    $var wire 32 " alu_a [31:0] $end
    $var wire 32 X alu_b [31:0] $end
    $var wire 3 ] alu_cd [2:0] $end
    $var wire 32 % alu_rd [31:0] $end
   $upscope $end
   $scope module c_0 $end
    $var wire 1 R clk $end
    $var wire 7 ` op [6:0] $end
    $var wire 3 a funct3 [2:0] $end
    $var wire 7 ` funct7 [6:0] $end
    $var wire 1 & r_cd $end
    $var wire 1 S dm_cd $end
    $var wire 1 Y m_cd1 $end
    $var wire 1 Z m_cd2 $end
    $var wire 1 [ d_cd1 $end
    $var wire 1 Y d_cd2 $end
    $var wire 2 \ e_cd [1:0] $end
    $var wire 3 ] alu_cd [2:0] $end
   $upscope $end
   $scope module demux_1 $end
    $var wire 32 # a1 [31:0] $end
    $var wire 1 [ d_cd $end
    $var wire 32 ) rd1 [31:0] $end
    $var wire 32 ( rd2 [31:0] $end
   $upscope $end
   $scope module demux_2 $end
    $var wire 32 % a1 [31:0] $end
    $var wire 1 Y d_cd $end
    $var wire 32 ^ rd1 [31:0] $end
    $var wire 32 % rd2 [31:0] $end
   $upscope $end
   $scope module e_0 $end
    $var wire 25 W e_a [24:0] $end
    $var wire 2 \ e_cd [1:0] $end
    $var wire 32 X e_rd [31:0] $end
   $upscope $end
   $scope module m_data $end
    $var wire 1 R clk $end
    $var wire 1 S dm_cd $end
    $var wire 32 ^ dm_a [31:0] $end
    $var wire 32 ( dm_wd [31:0] $end
    $var wire 32 ' dm_rd [31:0] $end
    $var wire 32 * data[0] [31:0] $end
    $var wire 32 + data[1] [31:0] $end
    $var wire 32 , data[2] [31:0] $end
    $var wire 32 - data[3] [31:0] $end
    $var wire 32 . data[4] [31:0] $end
    $var wire 32 / data[5] [31:0] $end
    $var wire 32 0 data[6] [31:0] $end
    $var wire 32 1 data[7] [31:0] $end
   $upscope $end
   $scope module m_inst $end
    $var wire 32 _ im_a [31:0] $end
    $var wire 32 _ im_rd [31:0] $end
    $var wire 32 b inst[0] [31:0] $end
    $var wire 32 c inst[1] [31:0] $end
    $var wire 32 d inst[2] [31:0] $end
    $var wire 32 e inst[3] [31:0] $end
    $var wire 32 f inst[4] [31:0] $end
    $var wire 32 g inst[5] [31:0] $end
    $var wire 32 h inst[6] [31:0] $end
    $var wire 32 i inst[7] [31:0] $end
   $upscope $end
   $scope module mux_1 $end
    $var wire 32 ) a1 [31:0] $end
    $var wire 32 X a2 [31:0] $end
    $var wire 1 Y m_cd $end
    $var wire 32 X m_rd [31:0] $end
   $upscope $end
   $scope module mux_2 $end
    $var wire 32 % a1 [31:0] $end
    $var wire 32 ' a2 [31:0] $end
    $var wire 1 Z m_cd $end
    $var wire 32 $ m_rd [31:0] $end
   $upscope $end
   $scope module r_0 $end
    $var wire 1 R clk $end
    $var wire 1 & r_cd $end
    $var wire 5 T r_a1 [4:0] $end
    $var wire 5 U r_a2 [4:0] $end
    $var wire 5 V r_a3 [4:0] $end
    $var wire 32 $ r_wd3 [31:0] $end
    $var wire 32 " r_rd1 [31:0] $end
    $var wire 32 # r_rd2 [31:0] $end
    $var wire 32 2 register[0] [31:0] $end
    $var wire 32 3 register[1] [31:0] $end
    $var wire 32 4 register[2] [31:0] $end
    $var wire 32 5 register[3] [31:0] $end
    $var wire 32 6 register[4] [31:0] $end
    $var wire 32 7 register[5] [31:0] $end
    $var wire 32 8 register[6] [31:0] $end
    $var wire 32 9 register[7] [31:0] $end
    $var wire 32 : register[8] [31:0] $end
    $var wire 32 ; register[9] [31:0] $end
    $var wire 32 < register[10] [31:0] $end
    $var wire 32 = register[11] [31:0] $end
    $var wire 32 > register[12] [31:0] $end
    $var wire 32 ? register[13] [31:0] $end
    $var wire 32 @ register[14] [31:0] $end
    $var wire 32 A register[15] [31:0] $end
    $var wire 32 B register[16] [31:0] $end
    $var wire 32 C register[17] [31:0] $end
    $var wire 32 D register[18] [31:0] $end
    $var wire 32 E register[19] [31:0] $end
    $var wire 32 F register[20] [31:0] $end
    $var wire 32 G register[21] [31:0] $end
    $var wire 32 H register[22] [31:0] $end
    $var wire 32 I register[23] [31:0] $end
    $var wire 32 J register[24] [31:0] $end
    $var wire 32 K register[25] [31:0] $end
    $var wire 32 L register[26] [31:0] $end
    $var wire 32 M register[27] [31:0] $end
    $var wire 32 N register[28] [31:0] $end
    $var wire 32 O register[29] [31:0] $end
    $var wire 32 P register[30] [31:0] $end
    $var wire 32 Q register[31] [31:0] $end
   $upscope $end
  $upscope $end
 $upscope $end
$enddefinitions $end


#1
b00000000000000000000000000000000 "
b00000000000000000000000000000000 #
b00000000000000000000000000001001 $
b00000000000000000000000000001001 %
0&
b00000000000000000000000000000000 '
b00000000000000000000000000000000 (
b00000000000000000000000000000000 )
b00000000000000000000000000000000 *
b00000000000000000000000000000000 +
b00000000000000000000000000000000 ,
b00000000000000000000000000000000 -
b00000000000000000000000000000000 .
b00000000000000000000000000000000 /
b00000000000000000000000000000000 0
b00000000000000000000000000000000 1
b00000000000000000000000000000000 2
b00000000000000000000000000000000 3
b00000000000000000000000000000000 4
b00000000000000000000000000000000 5
b00000000000000000000000000000000 6
b00000000000000000000000000000000 7
b00000000000000000000000000000000 8
b00000000000000000000000000000000 9
b00000000000000000000000000000000 :
b00000000000000000000000000000000 ;
b00000000000000000000000000000000 <
b00000000000000000000000000000000 =
b00000000000000000000000000000000 >
b00000000000000000000000000000000 ?
b00000000000000000000000000000000 @
b00000000000000000000000000000000 A
b00000000000000000000000000000000 B
b00000000000000000000000000000000 C
b00000000000000000000000000000000 D
b00000000000000000000000000000000 E
b00000000000000000000000000000000 F
b00000000000000000000000000000000 G
b00000000000000000000000000000000 H
b00000000000000000000000000000000 I
b00000000000000000000000000000000 J
b00000000000000000000000000000000 K
b00000000000000000000000000000000 L
b00000000000000000000000000000000 M
b00000000000000000000000000000000 N
b00000000000000000000000000000000 O
b00000000000000000000000000000000 P
b00000000000000000000000000000000 Q
1R
0S
b00011 T
b01001 U
b00101 V
b0000000010010001100000101 W
b00000000000000000000000000001001 X
1Y
0Z
0[
b01 \
b001 ]
b00000000000000000000000000000000 ^
b00000000100100011000001010000000 _
b0000000 `
b000 a
b00000000000000000000000000000000 b
b00000000000000000000000000000000 c
b00000000000000000000000000000000 d
b00000000000000000000000000000000 e
b00000000000000000000000000000000 f
b00000000000000000000000000000000 g
b00000000000000000000000000000000 h
b00000000000000000000000000000000 i
#2
0R
1S
#3
1&
b00000000000000000000000000001001 7
1R
#4
0R
0S
#5
0&
1R
#6
0R
1S
#7
1&
1R
#8
0R
0S
#9
0&
1R
#10
0R
1S
#11
1&
1R
#12
0R
0S
#13
0&
1R
#14
0R
1S
#15
1&
1R
#16
0R
0S
#17
0&
1R
#18
0R
1S
#19
1&
1R
#20
0R
0S
